<?xml version="1.0" encoding="UTF-8"?><androidapplication name="com.waze">
  <intent classname="com.facebook.internal.NativeProtocol" id="26" methodname="createPlatformServiceIntent" type="NEW">
    <outputcommunication>
      <outactions>
        <outaction>
          <action>com.facebook.platform.PLATFORM_SERVICE</action>
          <info/>
        </outaction>
      </outactions>
      <taintedness>
        <taintelement>
          <key>com.facebook.platform.protocol.METHOD_ARGS</key>
          <info/>
        </taintelement>
        <taintelement>
          <key>com.facebook.platform.protocol.BRIDGE_ARGS</key>
          <info/>
        </taintelement>
      </taintedness>
    </outputcommunication>
    <inputcommunication exists="true" exported="true"/>
  </intent>
  <intent classname="com.facebook.internal.NativeProtocol" id="28" methodname="findActivityIntent" type="NEW">
    <outputcommunication>
      <outactions>
        <outaction>
          <action>***</action>
          <info>Destination class not reachable: load 1 of type java.lang.String</info>
        </outaction>
      </outactions>
      <taintedness>
        <taintelement>
          <key>com.facebook.platform.protocol.BRIDGE_ARGS</key>
          <info/>
        </taintelement>
        <taintelement>
          <key>com.facebook.platform.protocol.METHOD_ARGS</key>
          <info/>
        </taintelement>
      </taintedness>
    </outputcommunication>
    <inputcommunication exists="true" exported="true"/>
  </intent>
  <intent classname="com.facebook.ProfileManager" id="101" methodname="sendCurrentProfileChangedBroadcast" type="NEW">
    <outputcommunication>
      <outactions>
        <outaction>
          <action>com.facebook.sdk.ACTION_CURRENT_PROFILE_CHANGED</action>
          <info/>
        </outaction>
      </outactions>
      <taintedness>
        <taintelement>
          <key>com.facebook.sdk.EXTRA_OLD_PROFILE</key>
          <info/>
        </taintelement>
        <taintelement>
          <key>com.facebook.sdk.EXTRA_NEW_PROFILE</key>
          <info/>
        </taintelement>
      </taintedness>
    </outputcommunication>
    <inputcommunication exists="true" exported="true"/>
  </intent>
  <intent classname="com.facebook.AccessTokenManager" id="113" methodname="sendCurrentAccessTokenChangedBroadcast" type="NEW">
    <outputcommunication>
      <outactions>
        <outaction>
          <action>com.facebook.sdk.ACTION_CURRENT_ACCESS_TOKEN_CHANGED</action>
          <info/>
        </outaction>
      </outactions>
      <taintedness>
        <taintelement>
          <key>com.facebook.sdk.EXTRA_NEW_ACCESS_TOKEN</key>
          <info/>
        </taintelement>
        <taintelement>
          <key>com.facebook.sdk.EXTRA_OLD_ACCESS_TOKEN</key>
          <info/>
        </taintelement>
      </taintedness>
    </outputcommunication>
    <inputcommunication exists="true" exported="true"/>
  </intent>
  <intent classname="com.waze.FreeMapAppActivity" id="246" methodname="carryOn" type="RECEIVED">
    <outputcommunication/>
    <inputcommunication exists="true" exported="true">
      <inactions>
        <inaction>android.intent.action.VIEW</inaction>
        <inaction>android.intent.action.MAIN</inaction>
      </inactions>
    </inputcommunication>
  </intent>
  <intent classname="com.google.android.gms.gcm.GcmReceiver" id="296" methodname="onStartWakefulService" type="PARAMETER">
    <outputcommunication/>
    <inputcommunication exists="true" exported="true">
      <inactions>
        <inaction>com.google.android.c2dm.intent.RECEIVE</inaction>
        <inaction>com.google.android.c2dm.intent.REGISTRATION</inaction>
      </inactions>
    </inputcommunication>
  </intent>
  <intent classname="com.google.android.gms.gcm.GcmReceiver" id="297" methodname="onReceive" type="PARAMETER">
    <outputcommunication>
      <outactions>
        <outaction>
          <action>com.google.android.gms.iid.InstanceID</action>
          <info/>
        </outaction>
      </outactions>
      <taintedness>
        <taintelement>
          <key>com.facebook.platform.protocol.BRIDGE_ARGS</key>
          <info/>
        </taintelement>
        <taintelement>
          <key>com.facebook.platform.protocol.BRIDGE_ARGS</key>
          <info/>
        </taintelement>
        <taintelement>
          <key>com.facebook.platform.protocol.BRIDGE_ARGS</key>
          <info/>
        </taintelement>
        <taintelement>
          <key>com.facebook.platform.protocol.BRIDGE_ARGS</key>
          <info/>
        </taintelement>
        <taintelement>
          <key>com.facebook.platform.protocol.BRIDGE_ARGS</key>
          <info/>
        </taintelement>
        <taintelement>
          <key>com.facebook.platform.protocol.BRIDGE_ARGS</key>
          <info/>
        </taintelement>
        <taintelement>
          <key>com.facebook.platform.protocol.BRIDGE_ARGS</key>
          <info/>
        </taintelement>
        <taintelement>
          <key>com.facebook.platform.protocol.BRIDGE_ARGS</key>
          <info/>
        </taintelement>
        <taintelement>
          <key>com.facebook.platform.protocol.BRIDGE_ARGS</key>
          <info/>
        </taintelement>
        <taintelement>
          <key>com.facebook.platform.protocol.BRIDGE_ARGS</key>
          <info/>
        </taintelement>
        <taintelement>
          <key>com.facebook.platform.protocol.BRIDGE_ARGS</key>
          <info/>
        </taintelement>
        <taintelement>
          <key>com.facebook.platform.protocol.BRIDGE_ARGS</key>
          <info/>
        </taintelement>
        <taintelement>
          <key>com.facebook.platform.protocol.BRIDGE_ARGS</key>
          <info/>
        </taintelement>
        <taintelement>
          <key>com.facebook.platform.protocol.BRIDGE_ARGS</key>
          <info/>
        </taintelement>
        <taintelement>
          <key>com.facebook.platform.protocol.BRIDGE_ARGS</key>
          <info/>
        </taintelement>
        <taintelement>
          <key>com.facebook.platform.protocol.BRIDGE_ARGS</key>
          <info/>
        </taintelement>
        <taintelement>
          <key>com.facebook.platform.protocol.BRIDGE_ARGS</key>
          <info/>
        </taintelement>
        <taintelement>
          <key>com.facebook.platform.protocol.BRIDGE_ARGS</key>
          <info/>
        </taintelement>
        <taintelement>
          <key>com.facebook.platform.protocol.BRIDGE_ARGS</key>
          <info/>
        </taintelement>
        <taintelement>
          <key>com.facebook.platform.protocol.BRIDGE_ARGS</key>
          <info/>
        </taintelement>
        <taintelement>
          <key>com.facebook.platform.protocol.BRIDGE_ARGS</key>
          <info/>
        </taintelement>
        <taintelement>
          <key>com.facebook.platform.protocol.BRIDGE_ARGS</key>
          <info/>
        </taintelement>
        <taintelement>
          <key>com.facebook.platform.protocol.BRIDGE_ARGS</key>
          <info/>
        </taintelement>
        <taintelement>
          <key>com.facebook.platform.protocol.BRIDGE_ARGS</key>
          <info/>
        </taintelement>
        <taintelement>
          <key>com.facebook.platform.protocol.BRIDGE_ARGS</key>
          <info/>
        </taintelement>
        <taintelement>
          <key>com.facebook.platform.protocol.BRIDGE_ARGS</key>
          <info/>
        </taintelement>
        <taintelement>
          <key>com.facebook.platform.protocol.BRIDGE_ARGS</key>
          <info/>
        </taintelement>
        <taintelement>
          <key>com.facebook.platform.protocol.BRIDGE_ARGS</key>
          <info/>
        </taintelement>
        <taintelement>
          <key>com.facebook.platform.protocol.BRIDGE_ARGS</key>
          <info/>
        </taintelement>
        <taintelement>
          <key>com.facebook.platform.protocol.BRIDGE_ARGS</key>
          <info/>
        </taintelement>
        <taintelement>
          <key>com.facebook.platform.protocol.BRIDGE_ARGS</key>
          <info/>
        </taintelement>
        <taintelement>
          <key>com.facebook.platform.protocol.BRIDGE_ARGS</key>
          <info/>
        </taintelement>
        <taintelement>
          <key>com.facebook.platform.protocol.BRIDGE_ARGS</key>
          <info/>
        </taintelement>
        <taintelement>
          <key>com.facebook.platform.protocol.BRIDGE_ARGS</key>
          <info/>
        </taintelement>
        <taintelement>
          <key>com.facebook.platform.protocol.BRIDGE_ARGS</key>
          <info/>
        </taintelement>
        <taintelement>
          <key>com.facebook.platform.protocol.BRIDGE_ARGS</key>
          <info/>
        </taintelement>
        <taintelement>
          <key>com.facebook.platform.protocol.BRIDGE_ARGS</key>
          <info/>
        </taintelement>
        <taintelement>
          <key>com.facebook.platform.protocol.BRIDGE_ARGS</key>
          <info/>
        </taintelement>
        <taintelement>
          <key>com.facebook.platform.protocol.BRIDGE_ARGS</key>
          <info/>
        </taintelement>
        <taintelement>
          <key>com.facebook.platform.protocol.BRIDGE_ARGS</key>
          <info/>
        </taintelement>
        <taintelement>
          <key>com.facebook.platform.protocol.BRIDGE_ARGS</key>
          <info/>
        </taintelement>
        <taintelement>
          <key>com.facebook.platform.protocol.BRIDGE_ARGS</key>
          <info/>
        </taintelement>
        <taintelement>
          <key>com.facebook.platform.protocol.BRIDGE_ARGS</key>
          <info/>
        </taintelement>
        <taintelement>
          <key>com.facebook.platform.protocol.BRIDGE_ARGS</key>
          <info/>
        </taintelement>
        <taintelement>
          <key>com.facebook.platform.protocol.BRIDGE_ARGS</key>
          <info/>
        </taintelement>
        <taintelement>
          <key>com.facebook.platform.protocol.BRIDGE_ARGS</key>
          <info/>
        </taintelement>
        <taintelement>
          <key>com.facebook.platform.protocol.BRIDGE_ARGS</key>
          <info/>
        </taintelement>
        <taintelement>
          <key>com.facebook.platform.protocol.BRIDGE_ARGS</key>
          <info/>
        </taintelement>
        <taintelement>
          <key>com.facebook.platform.protocol.BRIDGE_ARGS</key>
          <info/>
        </taintelement>
        <taintelement>
          <key>com.facebook.platform.protocol.METHOD_ARGS</key>
          <info/>
        </taintelement>
        <taintelement>
          <key>com.facebook.platform.protocol.METHOD_ARGS</key>
          <info/>
        </taintelement>
        <taintelement>
          <key>com.facebook.platform.protocol.METHOD_ARGS</key>
          <info/>
        </taintelement>
        <taintelement>
          <key>com.facebook.platform.protocol.METHOD_ARGS</key>
          <info/>
        </taintelement>
        <taintelement>
          <key>com.facebook.platform.protocol.METHOD_ARGS</key>
          <info/>
        </taintelement>
        <taintelement>
          <key>com.facebook.platform.protocol.METHOD_ARGS</key>
          <info/>
        </taintelement>
        <taintelement>
          <key>com.facebook.platform.protocol.METHOD_ARGS</key>
          <info/>
        </taintelement>
        <taintelement>
          <key>com.facebook.platform.protocol.METHOD_ARGS</key>
          <info/>
        </taintelement>
        <taintelement>
          <key>com.facebook.platform.protocol.METHOD_ARGS</key>
          <info/>
        </taintelement>
        <taintelement>
          <key>com.facebook.platform.protocol.METHOD_ARGS</key>
          <info/>
        </taintelement>
        <taintelement>
          <key>com.facebook.platform.protocol.METHOD_ARGS</key>
          <info/>
        </taintelement>
        <taintelement>
          <key>com.facebook.platform.protocol.METHOD_ARGS</key>
          <info/>
        </taintelement>
        <taintelement>
          <key>com.facebook.platform.protocol.METHOD_ARGS</key>
          <info/>
        </taintelement>
        <taintelement>
          <key>com.facebook.platform.protocol.METHOD_ARGS</key>
          <info/>
        </taintelement>
        <taintelement>
          <key>com.facebook.platform.protocol.METHOD_ARGS</key>
          <info/>
        </taintelement>
        <taintelement>
          <key>com.facebook.platform.protocol.METHOD_ARGS</key>
          <info/>
        </taintelement>
        <taintelement>
          <key>com.facebook.platform.protocol.METHOD_ARGS</key>
          <info/>
        </taintelement>
        <taintelement>
          <key>com.facebook.platform.protocol.METHOD_ARGS</key>
          <info/>
        </taintelement>
        <taintelement>
          <key>com.facebook.platform.protocol.METHOD_ARGS</key>
          <info/>
        </taintelement>
        <taintelement>
          <key>com.facebook.platform.protocol.METHOD_ARGS</key>
          <info/>
        </taintelement>
        <taintelement>
          <key>com.facebook.platform.protocol.METHOD_ARGS</key>
          <info/>
        </taintelement>
        <taintelement>
          <key>com.facebook.platform.protocol.METHOD_ARGS</key>
          <info/>
        </taintelement>
        <taintelement>
          <key>com.facebook.platform.protocol.METHOD_ARGS</key>
          <info/>
        </taintelement>
        <taintelement>
          <key>com.facebook.platform.protocol.METHOD_ARGS</key>
          <info/>
        </taintelement>
        <taintelement>
          <key>com.facebook.platform.protocol.METHOD_ARGS</key>
          <info/>
        </taintelement>
        <taintelement>
          <key>com.facebook.platform.protocol.METHOD_ARGS</key>
          <info/>
        </taintelement>
        <taintelement>
          <key>com.facebook.platform.protocol.METHOD_ARGS</key>
          <info/>
        </taintelement>
        <taintelement>
          <key>com.facebook.platform.protocol.METHOD_ARGS</key>
          <info/>
        </taintelement>
        <taintelement>
          <key>com.facebook.platform.protocol.METHOD_ARGS</key>
          <info/>
        </taintelement>
        <taintelement>
          <key>com.facebook.platform.protocol.METHOD_ARGS</key>
          <info/>
        </taintelement>
        <taintelement>
          <key>com.facebook.platform.protocol.METHOD_ARGS</key>
          <info/>
        </taintelement>
        <taintelement>
          <key>com.facebook.platform.protocol.METHOD_ARGS</key>
          <info/>
        </taintelement>
        <taintelement>
          <key>com.facebook.platform.protocol.METHOD_ARGS</key>
          <info/>
        </taintelement>
        <taintelement>
          <key>com.facebook.platform.protocol.METHOD_ARGS</key>
          <info/>
        </taintelement>
        <taintelement>
          <key>com.facebook.platform.protocol.METHOD_ARGS</key>
          <info/>
        </taintelement>
        <taintelement>
          <key>com.facebook.platform.protocol.METHOD_ARGS</key>
          <info/>
        </taintelement>
        <taintelement>
          <key>com.facebook.platform.protocol.METHOD_ARGS</key>
          <info/>
        </taintelement>
        <taintelement>
          <key>com.facebook.platform.protocol.METHOD_ARGS</key>
          <info/>
        </taintelement>
        <taintelement>
          <key>com.facebook.platform.protocol.METHOD_ARGS</key>
          <info/>
        </taintelement>
        <taintelement>
          <key>com.facebook.platform.protocol.METHOD_ARGS</key>
          <info/>
        </taintelement>
        <taintelement>
          <key>com.facebook.platform.protocol.METHOD_ARGS</key>
          <info/>
        </taintelement>
        <taintelement>
          <key>com.facebook.platform.protocol.METHOD_ARGS</key>
          <info/>
        </taintelement>
        <taintelement>
          <key>com.facebook.platform.protocol.METHOD_ARGS</key>
          <info/>
        </taintelement>
        <taintelement>
          <key>com.facebook.platform.protocol.METHOD_ARGS</key>
          <info/>
        </taintelement>
        <taintelement>
          <key>com.facebook.platform.protocol.METHOD_ARGS</key>
          <info/>
        </taintelement>
        <taintelement>
          <key>com.facebook.platform.protocol.METHOD_ARGS</key>
          <info/>
        </taintelement>
        <taintelement>
          <key>com.facebook.platform.protocol.METHOD_ARGS</key>
          <info/>
        </taintelement>
        <taintelement>
          <key>com.facebook.platform.protocol.METHOD_ARGS</key>
          <info/>
        </taintelement>
        <taintelement>
          <key>com.facebook.platform.protocol.METHOD_ARGS</key>
          <info/>
        </taintelement>
        <taintelement>
          <key>com.facebook.platform.protocol.METHOD_ARGS</key>
          <info/>
        </taintelement>
        <taintelement>
          <key>com.facebook.platform.protocol.METHOD_ARGS</key>
          <info/>
        </taintelement>
        <taintelement>
          <key>com.facebook.platform.protocol.METHOD_ARGS</key>
          <info/>
        </taintelement>
        <taintelement>
          <key>com.facebook.platform.protocol.METHOD_ARGS</key>
          <info/>
        </taintelement>
        <taintelement>
          <key>com.facebook.platform.protocol.METHOD_ARGS</key>
          <info/>
        </taintelement>
        <taintelement>
          <key>com.facebook.platform.protocol.METHOD_ARGS</key>
          <info/>
        </taintelement>
        <taintelement>
          <key>com.facebook.platform.protocol.METHOD_ARGS</key>
          <info/>
        </taintelement>
        <taintelement>
          <key>com.facebook.platform.protocol.METHOD_ARGS</key>
          <info/>
        </taintelement>
        <taintelement>
          <key>com.facebook.platform.protocol.METHOD_ARGS</key>
          <info/>
        </taintelement>
        <taintelement>
          <key>com.facebook.platform.protocol.METHOD_ARGS</key>
          <info/>
        </taintelement>
        <taintelement>
          <key>com.facebook.platform.protocol.METHOD_ARGS</key>
          <info/>
        </taintelement>
        <taintelement>
          <key>com.facebook.platform.protocol.METHOD_ARGS</key>
          <info/>
        </taintelement>
        <taintelement>
          <key>com.facebook.platform.protocol.METHOD_ARGS</key>
          <info/>
        </taintelement>
        <taintelement>
          <key>com.facebook.platform.protocol.METHOD_ARGS</key>
          <info/>
        </taintelement>
        <taintelement>
          <key>com.facebook.platform.protocol.METHOD_ARGS</key>
          <info/>
        </taintelement>
        <taintelement>
          <key>com.facebook.platform.protocol.METHOD_ARGS</key>
          <info/>
        </taintelement>
        <taintelement>
          <key>com.facebook.platform.protocol.METHOD_ARGS</key>
          <info/>
        </taintelement>
        <taintelement>
          <key>com.facebook.platform.protocol.METHOD_ARGS</key>
          <info/>
        </taintelement>
        <taintelement>
          <key>com.facebook.platform.protocol.METHOD_ARGS</key>
          <info/>
        </taintelement>
        <taintelement>
          <key>com.facebook.platform.protocol.METHOD_ARGS</key>
          <info/>
        </taintelement>
        <taintelement>
          <key>com.facebook.platform.protocol.METHOD_ARGS</key>
          <info/>
        </taintelement>
        <taintelement>
          <key>com.facebook.platform.protocol.METHOD_ARGS</key>
          <info/>
        </taintelement>
        <taintelement>
          <key>com.facebook.platform.protocol.METHOD_ARGS</key>
          <info/>
        </taintelement>
        <taintelement>
          <key>com.facebook.platform.protocol.METHOD_ARGS</key>
          <info/>
        </taintelement>
        <taintelement>
          <key>com.facebook.platform.protocol.METHOD_ARGS</key>
          <info/>
        </taintelement>
        <taintelement>
          <key>com.facebook.platform.protocol.METHOD_ARGS</key>
          <info/>
        </taintelement>
        <taintelement>
          <key>com.facebook.platform.protocol.METHOD_ARGS</key>
          <info/>
        </taintelement>
        <taintelement>
          <key>com.facebook.platform.protocol.METHOD_ARGS</key>
          <info/>
        </taintelement>
        <taintelement>
          <key>com.facebook.platform.protocol.METHOD_ARGS</key>
          <info/>
        </taintelement>
        <taintelement>
          <key>com.facebook.platform.protocol.METHOD_ARGS</key>
          <info/>
        </taintelement>
        <taintelement>
          <key>com.facebook.platform.protocol.METHOD_ARGS</key>
          <info/>
        </taintelement>
        <taintelement>
          <key>com.facebook.platform.protocol.METHOD_ARGS</key>
          <info/>
        </taintelement>
        <taintelement>
          <key>com.facebook.platform.protocol.METHOD_ARGS</key>
          <info/>
        </taintelement>
        <taintelement>
          <key>com.facebook.platform.protocol.METHOD_ARGS</key>
          <info/>
        </taintelement>
        <taintelement>
          <key>com.facebook.platform.protocol.METHOD_ARGS</key>
          <info/>
        </taintelement>
        <taintelement>
          <key>com.facebook.platform.protocol.METHOD_ARGS</key>
          <info/>
        </taintelement>
        <taintelement>
          <key>com.facebook.platform.protocol.METHOD_ARGS</key>
          <info/>
        </taintelement>
        <taintelement>
          <key>com.facebook.platform.protocol.METHOD_ARGS</key>
          <info/>
        </taintelement>
        <taintelement>
          <key>com.facebook.platform.protocol.METHOD_ARGS</key>
          <info/>
        </taintelement>
        <taintelement>
          <key>com.facebook.platform.protocol.METHOD_ARGS</key>
          <info/>
        </taintelement>
        <taintelement>
          <key>com.facebook.platform.protocol.METHOD_ARGS</key>
          <info/>
        </taintelement>
        <taintelement>
          <key>com.facebook.platform.protocol.METHOD_ARGS</key>
          <info/>
        </taintelement>
        <taintelement>
          <key>com.facebook.platform.protocol.METHOD_ARGS</key>
          <info/>
        </taintelement>
        <taintelement>
          <key>com.facebook.platform.protocol.METHOD_ARGS</key>
          <info/>
        </taintelement>
        <taintelement>
          <key>com.facebook.platform.protocol.METHOD_ARGS</key>
          <info/>
        </taintelement>
        <taintelement>
          <key>com.facebook.platform.protocol.METHOD_ARGS</key>
          <info/>
        </taintelement>
        <taintelement>
          <key>com.facebook.platform.protocol.METHOD_ARGS</key>
          <info/>
        </taintelement>
        <taintelement>
          <key>com.facebook.platform.protocol.METHOD_ARGS</key>
          <info/>
        </taintelement>
        <taintelement>
          <key>com.facebook.platform.protocol.METHOD_ARGS</key>
          <info/>
        </taintelement>
        <taintelement>
          <key>com.facebook.platform.protocol.BRIDGE_ARGS</key>
          <info/>
        </taintelement>
        <taintelement>
          <key>com.facebook.platform.protocol.BRIDGE_ARGS</key>
          <info/>
        </taintelement>
        <taintelement>
          <key>com.facebook.platform.protocol.BRIDGE_ARGS</key>
          <info/>
        </taintelement>
        <taintelement>
          <key>com.facebook.platform.protocol.BRIDGE_ARGS</key>
          <info/>
        </taintelement>
        <taintelement>
          <key>com.facebook.platform.protocol.BRIDGE_ARGS</key>
          <info/>
        </taintelement>
        <taintelement>
          <key>com.facebook.platform.protocol.BRIDGE_ARGS</key>
          <info/>
        </taintelement>
        <taintelement>
          <key>com.facebook.platform.protocol.BRIDGE_ARGS</key>
          <info/>
        </taintelement>
        <taintelement>
          <key>com.facebook.platform.protocol.BRIDGE_ARGS</key>
          <info/>
        </taintelement>
        <taintelement>
          <key>com.facebook.platform.protocol.BRIDGE_ARGS</key>
          <info/>
        </taintelement>
        <taintelement>
          <key>com.facebook.platform.protocol.BRIDGE_ARGS</key>
          <info/>
        </taintelement>
        <taintelement>
          <key>com.facebook.platform.protocol.BRIDGE_ARGS</key>
          <info/>
        </taintelement>
        <taintelement>
          <key>com.facebook.platform.protocol.BRIDGE_ARGS</key>
          <info/>
        </taintelement>
        <taintelement>
          <key>com.facebook.platform.protocol.BRIDGE_ARGS</key>
          <info/>
        </taintelement>
        <taintelement>
          <key>com.facebook.platform.protocol.BRIDGE_ARGS</key>
          <info/>
        </taintelement>
        <taintelement>
          <key>com.facebook.platform.protocol.BRIDGE_ARGS</key>
          <info/>
        </taintelement>
        <taintelement>
          <key>com.facebook.platform.protocol.BRIDGE_ARGS</key>
          <info/>
        </taintelement>
        <taintelement>
          <key>com.facebook.platform.protocol.BRIDGE_ARGS</key>
          <info/>
        </taintelement>
        <taintelement>
          <key>com.facebook.platform.protocol.BRIDGE_ARGS</key>
          <info/>
        </taintelement>
        <taintelement>
          <key>com.facebook.platform.protocol.BRIDGE_ARGS</key>
          <info/>
        </taintelement>
        <taintelement>
          <key>com.facebook.platform.protocol.BRIDGE_ARGS</key>
          <info/>
        </taintelement>
        <taintelement>
          <key>com.facebook.platform.protocol.BRIDGE_ARGS</key>
          <info/>
        </taintelement>
        <taintelement>
          <key>com.facebook.platform.protocol.BRIDGE_ARGS</key>
          <info/>
        </taintelement>
        <taintelement>
          <key>com.facebook.platform.protocol.BRIDGE_ARGS</key>
          <info/>
        </taintelement>
        <taintelement>
          <key>com.facebook.platform.protocol.BRIDGE_ARGS</key>
          <info/>
        </taintelement>
        <taintelement>
          <key>com.facebook.platform.protocol.BRIDGE_ARGS</key>
          <info/>
        </taintelement>
        <taintelement>
          <key>com.facebook.platform.protocol.BRIDGE_ARGS</key>
          <info/>
        </taintelement>
        <taintelement>
          <key>com.facebook.platform.protocol.BRIDGE_ARGS</key>
          <info/>
        </taintelement>
        <taintelement>
          <key>com.facebook.platform.protocol.BRIDGE_ARGS</key>
          <info/>
        </taintelement>
        <taintelement>
          <key>com.facebook.platform.protocol.BRIDGE_ARGS</key>
          <info/>
        </taintelement>
        <taintelement>
          <key>com.facebook.platform.protocol.BRIDGE_ARGS</key>
          <info/>
        </taintelement>
        <taintelement>
          <key>com.facebook.platform.protocol.BRIDGE_ARGS</key>
          <info/>
        </taintelement>
        <taintelement>
          <key>com.facebook.platform.protocol.BRIDGE_ARGS</key>
          <info/>
        </taintelement>
        <taintelement>
          <key>com.facebook.platform.protocol.BRIDGE_ARGS</key>
          <info/>
        </taintelement>
        <taintelement>
          <key>com.facebook.platform.protocol.BRIDGE_ARGS</key>
          <info/>
        </taintelement>
        <taintelement>
          <key>com.facebook.platform.protocol.BRIDGE_ARGS</key>
          <info/>
        </taintelement>
        <taintelement>
          <key>com.facebook.platform.protocol.BRIDGE_ARGS</key>
          <info/>
        </taintelement>
        <taintelement>
          <key>com.facebook.platform.protocol.BRIDGE_ARGS</key>
          <info/>
        </taintelement>
        <taintelement>
          <key>com.facebook.platform.protocol.BRIDGE_ARGS</key>
          <info/>
        </taintelement>
        <taintelement>
          <key>com.facebook.platform.protocol.BRIDGE_ARGS</key>
          <info/>
        </taintelement>
        <taintelement>
          <key>com.facebook.platform.protocol.BRIDGE_ARGS</key>
          <info/>
        </taintelement>
        <taintelement>
          <key>com.facebook.platform.protocol.BRIDGE_ARGS</key>
          <info/>
        </taintelement>
        <taintelement>
          <key>com.facebook.platform.protocol.BRIDGE_ARGS</key>
          <info/>
        </taintelement>
        <taintelement>
          <key>com.facebook.platform.protocol.BRIDGE_ARGS</key>
          <info/>
        </taintelement>
        <taintelement>
          <key>com.facebook.platform.protocol.BRIDGE_ARGS</key>
          <info/>
        </taintelement>
        <taintelement>
          <key>com.facebook.platform.protocol.BRIDGE_ARGS</key>
          <info/>
        </taintelement>
        <taintelement>
          <key>com.facebook.platform.protocol.BRIDGE_ARGS</key>
          <info/>
        </taintelement>
        <taintelement>
          <key>com.facebook.platform.protocol.BRIDGE_ARGS</key>
          <info/>
        </taintelement>
        <taintelement>
          <key>com.facebook.platform.protocol.BRIDGE_ARGS</key>
          <info/>
        </taintelement>
        <taintelement>
          <key>com.facebook.platform.protocol.BRIDGE_ARGS</key>
          <info/>
        </taintelement>
      </taintedness>
    </outputcommunication>
    <inputcommunication exists="true" exported="true">
      <inactions>
        <inaction>com.google.android.c2dm.intent.RECEIVE</inaction>
        <inaction>com.google.android.c2dm.intent.REGISTRATION</inaction>
      </inactions>
    </inputcommunication>
  </intent>
  <intent classname="com.google.android.gms.gcm.GcmReceiver" id="298" methodname="zzg" type="PARAMETER">
    <outputcommunication/>
    <inputcommunication exists="true" exported="true">
      <inactions>
        <inaction>com.google.android.c2dm.intent.RECEIVE</inaction>
        <inaction>com.google.android.c2dm.intent.REGISTRATION</inaction>
      </inactions>
    </inputcommunication>
  </intent>
  <intent classname="com.google.android.gms.gcm.GcmReceiver" id="299" methodname="zzh" type="PARAMETER">
    <outputcommunication/>
    <inputcommunication exists="true" exported="true">
      <inactions>
        <inaction>com.google.android.c2dm.intent.RECEIVE</inaction>
        <inaction>com.google.android.c2dm.intent.REGISTRATION</inaction>
      </inactions>
    </inputcommunication>
  </intent>
  <intent classname="com.waze.CalendarChangeReceiver" id="342" methodname="onReceive" type="PARAMETER">
    <outputcommunication/>
    <inputcommunication exists="true" exported="true">
      <inactions>
        <inaction>android.intent.action.PROVIDER_CHANGED</inaction>
      </inactions>
    </inputcommunication>
  </intent>
</androidapplication>
